setup.py
salarycalculatorsda/__init__.py
salarycalculatorsda/calc_salary.py
salarycalculatorsda.egg-info/PKG-INFO
salarycalculatorsda.egg-info/SOURCES.txt
salarycalculatorsda.egg-info/dependency_links.txt
salarycalculatorsda.egg-info/top_level.txt